pre_commit_crocodile/__init__.py
pre_commit_crocodile/__main__.py
pre_commit_crocodile/assets/.cz.yaml
pre_commit_crocodile/assets/.pre-commit-config.template.yaml
pre_commit_crocodile/assets/__init__.py
pre_commit_crocodile/assets/commits.yml
pre_commit_crocodile/cli/__init__.py
pre_commit_crocodile/cli/entrypoint.py
pre_commit_crocodile/cli/main.py
pre_commit_crocodile/features/__init__.py
pre_commit_crocodile/features/argcomplete.py
pre_commit_crocodile/features/commitizen.py
pre_commit_crocodile/features/gcil.py
pre_commit_crocodile/features/git.py
pre_commit_crocodile/features/precommit.py
pre_commit_crocodile/features/prek.py
pre_commit_crocodile/features/radiandevcore.py
pre_commit_crocodile/features/readme.py
pre_commit_crocodile/features/templates.py
pre_commit_crocodile/hooks/__init__.py
pre_commit_crocodile/hooks/check_commitizen_branch.py
pre_commit_crocodile/hooks/check_yaml_ruamel_pure.py
pre_commit_crocodile/hooks/configurations.py
pre_commit_crocodile/hooks/prepare_commit_message.py
pre_commit_crocodile/package/__init__.py
pre_commit_crocodile/package/bundle.py
pre_commit_crocodile/package/settings.py
pre_commit_crocodile/package/updates.py
pre_commit_crocodile/package/version.py
pre_commit_crocodile/prints/__init__.py
pre_commit_crocodile/prints/boxes.py
pre_commit_crocodile/prints/colors.py
pre_commit_crocodile/system/__init__.py
pre_commit_crocodile/system/commands.py
pre_commit_crocodile/system/platform.py
pre_commit_crocodile/types/__init__.py
pre_commit_crocodile/types/environments.py
pre_commit_crocodile/types/strings.py
pre_commit_crocodile-8.2.1.dist-info/licenses/LICENSE
pre_commit_crocodile-8.2.1.dist-info/METADATA
pre_commit_crocodile-8.2.1.dist-info/WHEEL
pre_commit_crocodile-8.2.1.dist-info/entry_points.txt
pre_commit_crocodile-8.2.1.dist-info/top_level.txt
pre_commit_crocodile-8.2.1.dist-info/RECORD
